sigma/backends/matano/__init__.py
sigma/backends/matano/matano.py
sigma/pipelines/.gitkeep
pysigma_backend_matano-0.0.1.dist-info/LICENSE
pysigma_backend_matano-0.0.1.dist-info/WHEEL
pysigma_backend_matano-0.0.1.dist-info/METADATA
pysigma_backend_matano-0.0.1.dist-info/RECORD
