Metadata-Version: 2.1
Name: pysigma-backend-matano
Version: 0.0.1
Summary: Matano backend for pySigma. Convert Sigma rules into Matano detections.
Home-page: https://github.com/matanolabs/pySigma-backend-matano
License: Apache-2.0
Author: Samrose Ahmed
Author-email: samrose@matano.dev
Requires-Python: >=3.8,<4.0
Classifier: Intended Audience :: Developers
Classifier: License :: OSI Approved :: Apache Software License
Classifier: Programming Language :: Python :: 3
Classifier: Programming Language :: Python :: 3.8
Classifier: Programming Language :: Python :: 3.9
Classifier: Programming Language :: Python :: 3.10
Classifier: Programming Language :: Python :: 3.10
Classifier: Programming Language :: Python :: 3.8
Classifier: Programming Language :: Python :: 3.9
Classifier: Topic :: Security
Requires-Dist: black (>=22.8.0,<23.0.0)
Requires-Dist: pysigma (>=0.8.1,<0.9.0)
Project-URL: Repository, https://github.com/matanolabs/pySigma-backend-matano
